high_sql/__init__.py
high_sql/abstract_highsql.py
high_sql/high_config.py
high_sql/high_mysql.py
high_sql/sql_schema.json
high_sql-1.0.2.data/data/sql_schema.json
tests/__init__.py
tests/test_high_sql.py
high_sql-1.0.2.dist-info/LICENSE
high_sql-1.0.2.dist-info/METADATA
high_sql-1.0.2.dist-info/WHEEL
high_sql-1.0.2.dist-info/entry_points.txt
high_sql-1.0.2.dist-info/top_level.txt
high_sql-1.0.2.dist-info/RECORD
