Metadata-Version: 2.1
Name: high-sql
Version: 1.0.2
Summary: A high-level sql command utility. Currently only MySQL is supported.
Home-page: https://github.com/drkostas/high-sql/tree/master/
Author: Kostas Georgiou
Author-email: georgiou.kostas94@gmail.com
License: Apache Software License 2.0
Keywords: db,database,wrapper,connection,high-level,commands,sql,mysql,nosql,mongodb,postgresql
Platform: UNKNOWN
Classifier: Development Status :: 5 - Production/Stable
Classifier: Intended Audience :: Developers
Classifier: License :: OSI Approved :: Apache Software License
Classifier: Natural Language :: English
Classifier: Programming Language :: Python :: 3.6
Classifier: Programming Language :: Python :: 3.7
Classifier: Programming Language :: Python :: 3.8
Requires-Python: >=3.6
License-File: LICENSE
Requires-Dist: mysql-connector-python (~=8.0.19)
Requires-Dist: mysql-connector (~=2.2.9)
Requires-Dist: yaml-config-wrapper (>=1.0.4)
Requires-Dist: termcolor-logger (>=1.0.3)
